{
  "hash": "e4f93286",
  "configHash": "3570371b",
  "lockfileHash": "3c25f971",
  "browserHash": "e1862336",
  "optimized": {
    "react": {
      "src": "../../node_modules/react/index.js",
      "file": "react.js",
      "fileHash": "a1e92bb6",
      "needsInterop": true
    },
    "react-dom/client": {
      "src": "../../node_modules/react-dom/client.js",
      "file": "react-dom_client.js",
      "fileHash": "83f49a01",
      "needsInterop": true
    }
  },
  "chunks": {
    "chunk-Y455YYDO": {
      "file": "chunk-Y455YYDO.js"
    }
  }
}